django/__init__.py
django/__main__.py
django/shortcuts.py
django_otp/__init__.py
django_otp/admin.py
django_otp/conf.py
django_otp/decorators.py
django_otp/forms.py
django_otp/middleware.py
django_otp/models.py
django_otp/oath.py
django_otp/setup.py
django_otp/tests.py
django_otp/util.py
django_otp/views.py
two_factor/__init__.py
two_factor/admin.py
two_factor/apps.py
two_factor/forms.py
two_factor/signals.py
two_factor/urls.py
two_factor/utils.py
ognajd-0.1.dist-info/METADATA
ognajd-0.1.dist-info/WHEEL
ognajd-0.1.dist-info/top_level.txt
ognajd-0.1.dist-info/RECORD
