Metadata-Version: 2.1
Name: ognajd
Version: 0.1
Summary: .
Home-page: UNKNOWN
Author: John
Author-email: john@world.com
License: UNKNOWN
Platform: UNKNOWN
Classifier: Programming Language :: Python :: 3
Classifier: License :: OSI Approved :: MIT License
Classifier: Operating System :: OS Independent
